{
   "tiers": [
      {
         "trades": [
            {
               "wants": [
                  {
                     "item": "cosmos:lunar_sapphire",
                     "quantity": {
                        "min": 1,
                        "max": 2
                     }
                  }
               ],
               "gives": [
                  {
                     "item": "cosmos:oxygen_mask"
                  }
               ]
            },
            {
               "wants": [
                  {
                     "item": "cosmos:lunar_sapphire",
                     "quantity": {
                        "min": 3,
                        "max": 4
                     }
                  }
               ],
               "gives": [
                  {
                     "item": "cosmos:oxygen_tank_light_full",
                     "functions": [
                        {
                           "function": "set_damage",
                           "damage": 0.765
                        }
                     ]
                  }
               ]
            },
            {
               "wants": [
                  {
                     "item": "cosmos:lunar_sapphire",
                     "quantity": {
                        "min": 3,
                        "max": 4
                     }
                  }
               ],
               "gives": [
                  {
                     "item": "cosmos:oxygen_gear"
                  }
               ]
            },
            {
               "wants": [
                  {
                     "item": "cosmos:lunar_sapphire",
                     "quantity": {
                        "min": 3,
                        "max": 4
                     }
                  }
               ],
               "gives": [
                  {
                     "item": "cosmos:fuel_canister"
                  }
               ]
            },
            {
               "wants": [
                  {
                     "item": "cosmos:lunar_sapphire",
                     "quantity": {
                        "min": 1,
                        "max": 2
                     }
                  }
               ],
               "gives": [
                  {
                     "item": "cosmos:parachute_plain"
                  }
               ]
            },
            {
               "wants": [
                  {
                     "item": "cosmos:lunar_sapphire",
                     "quantity": {
                        "min": 2,
                        "max": 4
                     }
                  }
               ],
               "gives": [
                  {
                     "item": "cosmos:battery",
                     "functions": [
                        {
                           "function": "set_damage",
                           "damage": 0.42
                        },
                        {
                           "function": "set_lore",
                           "lore": [
                              "ยงrยง66300/15,000 gJ"
                           ]
                        }
                     ]
                  }
               ]
            },
            {
               "wants": [
                  {
                     "item": "cosmos:lunar_sapphire"
                  },
                  {
                     "item": "cosmos:empty_canister"
                  }
               ],
               "gives": [
                  {
                     "item": "cosmos:dehydrated_carrot"
                  }
               ]
            },
            {
               "wants": [
                  {
                     "item": "cosmos:lunar_sapphire",
                     "quantity": {
                        "min": 3,
                        "max": 4
                     }
                  }
               ],
               "gives": [
                  {
                     "item": "cosmos:basic_wafer"
                  }
               ]
            },
            {
               "wants": [
                  {
                     "item": "cosmos:schematic_buggy"
                  },
                  {
                     "item": "cosmos:lunar_sapphire",
                     "quantity": {
                        "min": 3,
                        "max": 5
                     }
                  }
               ],
               "gives": [
                  {
                     "item": "cosmos:schematic_rocket_t2"
                  }
               ]
            },
            {
               "wants": [
                  {
                     "item": "cosmos:schematic_rocket_t2"
                  },
                  {
                     "item": "cosmos:lunar_sapphire",
                     "quantity": {
                        "min": 3,
                        "max": 5
                     }
                  }
               ],
               "gives": [
                  {
                     "item": "cosmos:schematic_buggy"
                  }
               ]
            },
            {
               "wants": [
                  {
                     "item": "cosmos:tin_ingot",
                     "quantity": {
                        "min": 2,
                        "max": 2
                     }
                  },
                  {
                     "item": "cosmos:lunar_sapphire"
                  }
               ],
               "gives": [
                  {
                     "item": "cosmos:compressed_tin"
                  }
               ]
            },
            {
               "wants": [
                  {
                     "item": "minecraft:copper_ingot",
                     "quantity": {
                        "min": 2,
                        "max": 2
                     }
                  },
                  {
                     "item": "cosmos:lunar_sapphire"
                  }
               ],
               "gives": [
                  {
                     "item": "cosmos:compressed_copper"
                  }
               ]
            },
            {
               "wants": [
                  {
                     "item": "minecraft:jungle_sapling",
                     "quantity": {
                        "min": 15,
                        "max": 40
                     }
                  }
               ],
               "gives": [
                  {
                     "item": "cosmos:lunar_sapphire"
                  }
               ]
            }
         ]
      }
   ]
}